tidybib/__init__.py
tidybib/__main__.py
tidybib/biblib.py
tidybib/inputfiles.py
tidybib-0.1.3.dist-info/LICENSE
tidybib-0.1.3.dist-info/METADATA
tidybib-0.1.3.dist-info/WHEEL
tidybib-0.1.3.dist-info/entry_points.txt
tidybib-0.1.3.dist-info/top_level.txt
tidybib-0.1.3.dist-info/RECORD
