Metadata-Version: 2.1
Name: tidybib
Version: 0.1.3
Summary: BibTeX formatter
Author-email: Nicolas Tessore <n.tessore@ucl.ac.uk>
License: MIT License
Project-URL: Homepage, https://github.com/ntessore/tidybib
Keywords: tex,latex,bibtex,formatter
Requires-Python: >=3.10
License-File: LICENSE
